spnexus/__init__.py
spnexus/base.py
spnexus/events/emitter.py
spnexus/events/event.py
spnexus/events/exceptions.py
spnexus/mutables/base.py
spnexus/utils/base.py
spnexus/utils/data.py
spnexus/utils/dict.py
spnexus/utils/lists.py
spnexus/utils/paths.py
spnexus/utils/regex.py
spnexus/utils/serialization.py
spnexus/utils/shapefile.py
spnexus-0.0.62.dist-info/LICENSE
spnexus-0.0.62.dist-info/METADATA
spnexus-0.0.62.dist-info/WHEEL
spnexus-0.0.62.dist-info/top_level.txt
spnexus-0.0.62.dist-info/RECORD
