Metadata-Version: 2.1
Name: spnexus
Version: 0.0.62
Summary: SPNexus or Service Provider Nexus is an aggregation library of mini-framework solutions used in various Azorian Solutions software projects.
Author-email: Matt Scott <matt@azorian.solutions>
License: GNU GENERAL PUBLIC LICENSE
Project-URL: Homepage, https://gitlab.azorian.solutions/as-libs/spnexus
Project-URL: Bug Tracker, https://gitlab.azorian.solutions/as-libs/spnexus/-/issues
Classifier: Programming Language :: Python :: 3
Classifier: License :: OSI Approved :: GNU Lesser General Public License v3 or later (LGPLv3+)
Classifier: Operating System :: OS Independent
Requires-Python: >=3.7
License-File: LICENSE
